deepnlp2025/__cli__.py
deepnlp2025/__init__.py
deepnlp2025/_version.py
deepnlp2025/py.typed
deepnlp2025/conf/about/deepnlp2025.yaml
deepnlp_2025-0.2.0.dist-info/METADATA
deepnlp_2025-0.2.0.dist-info/WHEEL
deepnlp_2025-0.2.0.dist-info/entry_points.txt
deepnlp_2025-0.2.0.dist-info/licenses/LICENSE
deepnlp_2025-0.2.0.dist-info/RECORD
