Metadata-Version: 2.4
Name: deepnlp-2025
Version: 0.2.0
Summary: Advanced deep learning techniques for natural language processing with modern architectures and Korean language applications
Project-URL: Homepage, https://deepnlp2025.jeju.ai
Project-URL: Repository, https://github.com/entelecheia/deepnlp-2025
Project-URL: Documentation, https://deepnlp2025.jeju.ai
Author-email: Young Joon Lee <entelecheia@hotmail.com>
License-Expression: CC-BY-4.0
License-File: LICENSE
Keywords: python
Classifier: Intended Audience :: Developers
Classifier: Programming Language :: Python
Classifier: Programming Language :: Python :: 3
Classifier: Programming Language :: Python :: 3.9
Classifier: Programming Language :: Python :: 3.10
Classifier: Programming Language :: Python :: 3.11
Classifier: Programming Language :: Python :: 3.12
Classifier: Programming Language :: Python :: 3.13
Classifier: Topic :: Software Development :: Libraries :: Python Modules
Requires-Python: <4.0,>=3.9
Requires-Dist: click>=8.1.7
